tokenpdf/__init__.py
tokenpdf/__main__.py
tokenpdf/image.py
tokenpdf/resources.py
tokenpdf/canvas/__init__.py
tokenpdf/canvas/canvas.py
tokenpdf/canvas/reportlab.py
tokenpdf/data/example.toml
tokenpdf/data/systems/dnd5e.toml
tokenpdf/layouts/__init__.py
tokenpdf/layouts/greedy.py
tokenpdf/layouts/layout.py
tokenpdf/layouts/rectpack.py
tokenpdf/maps/__init__.py
tokenpdf/maps/map.py
tokenpdf/maps/mapper.py
tokenpdf/maps/simple.py
tokenpdf/pipeline/canvas.py
tokenpdf/pipeline/layout.py
tokenpdf/pipeline/post.py
tokenpdf/pipeline/tokens.py
tokenpdf/pipeline/workflow.py
tokenpdf/systems/__init__.py
tokenpdf/systems/system.py
tokenpdf/token/__init__.py
tokenpdf/token/circle.py
tokenpdf/token/stand.py
tokenpdf/token/token.py
tokenpdf/utils/__init__.py
tokenpdf/utils/config.py
tokenpdf/utils/general.py
tokenpdf/utils/geometry.py
tokenpdf/utils/graph.py
tokenpdf/utils/image.py
tokenpdf/utils/io.py
tokenpdf/utils/verbose.py
tokenpdf-0.3.dist-info/LICENSE
tokenpdf-0.3.dist-info/METADATA
tokenpdf-0.3.dist-info/WHEEL
tokenpdf-0.3.dist-info/entry_points.txt
tokenpdf-0.3.dist-info/top_level.txt
tokenpdf-0.3.dist-info/RECORD
