Metadata-Version: 2.2
Name: tokenpdf
Version: 0.3
Summary: Generate printable PDF files for tabletop RPG tokens and maps
Home-page: https://github.com/Dormar2/tokenpdf
Author: Dor Marciano
Author-email: doormarci@gmail.com
License: MIT
Classifier: Programming Language :: Python :: 3
Classifier: License :: OSI Approved :: MIT License
Classifier: Operating System :: OS Independent
Classifier: Topic :: Games/Entertainment :: Role-Playing
Requires-Python: >=3.10
License-File: LICENSE
Requires-Dist: numpy
Requires-Dist: Pillow
Requires-Dist: papersize
Requires-Dist: reportlab
Requires-Dist: toml
Requires-Dist: pyyaml
Requires-Dist: requests
Requires-Dist: networkx
Requires-Dist: platformdirs
Requires-Dist: tqdm
Requires-Dist: wrapt
Requires-Dist: rectpack
Requires-Dist: imagesize
Requires-Dist: pikepdf
Requires-Dist: tabulate
Requires-Dist: PyMuPDF
Dynamic: author
Dynamic: author-email
Dynamic: classifier
Dynamic: description
Dynamic: description-content-type
Dynamic: home-page
Dynamic: license
Dynamic: requires-dist
Dynamic: requires-python
Dynamic: summary
